<?xml version="1.0" encoding="UTF-8"?>
<AssetDeclaration
	xmlns="uri:ea.com:eala:asset"
	xmlns:xsi="http://www.w3.org/2001/XMLSchema-instance">
	<Tags/>
	<Includes>
		<Include
			source="DATA:static.xml"
			type="reference"/>
		<Include
			source="DATA:global.xml"
			type="reference"/>
		<Include
			source="ART:BleachByPass_vol.xml"
			type="instance"/>
		<Include
			source="ART:CM_RedZoneA_LightRays.xml"
			type="instance"/>
		<Include
			source="ART:EVDefault.xml"
			type="instance"/>
		<Include
			source="ART:TSCloudMed.xml"
			type="instance"/>
		<Include
			source="ART:TSNoiseUrb.xml"
			type="instance"/>
		<Include
			source="DATA:GlobalData/roads.xml"
			type="instance"/>
		<Include
			source="DATA:civilian/australia_as/trees/astdead01.xml"
			type="instance"/>
		<Include
			source="DATA:civilian/australia_as/trees/astdead02.xml"
			type="instance"/>
		<Include
			source="DATA:civilian/australia_as/trees/astdead02a.xml"
			type="instance"/>
		<Include
			source="DATA:civilian/australia_as/trees/astdead03.xml"
			type="instance"/>
		<Include
			source="DATA:civilian/australia_as/trees/astdead04.xml"
			type="instance"/>
		<Include
			source="DATA:civilian/australia_as/trees/astdead05.xml"
			type="instance"/>
		<Include
			source="DATA:civilian/australia_as/trees/astdead06.xml"
			type="instance"/>
		<Include
			source="DATA:civilian/australia_as/trees/astshrub01.xml"
			type="instance"/>
		<Include
			source="DATA:civilian/buildings/rubbledbuilding02.xml"
			type="instance"/>
		<Include
			source="DATA:civilian/buildings/rubbledbuilding03.xml"
			type="instance"/>
		<Include
			source="DATA:civilian/buildings/rubbledbuilding04.xml"
			type="instance"/>
		<Include
			source="DATA:civilian/italy_it/buildings/itbrui19.xml"
			type="instance"/>
		<Include
			source="DATA:civilian/italy_it/buildings/itbrui21.xml"
			type="instance"/>
		<Include
			source="DATA:civilian/italy_it/buildings/itbrui22.xml"
			type="instance"/>
		<Include
			source="DATA:civilian/italy_it/buildings/itbrui23.xml"
			type="instance"/>
		<Include
			source="DATA:civilian/italy_it/buildings/itbrui24.xml"
			type="instance"/>
		<Include
			source="DATA:civilian/italy_it/buildings/itbrui25.xml"
			type="instance"/>
		<Include
			source="DATA:civilian/italy_it/buildings/itbrui29.xml"
			type="instance"/>
		<Include
			source="DATA:civilian/italy_it/props/itpdeadp01.xml"
			type="instance"/>
		<Include
			source="DATA:civilian/italy_it/props/itpdeadp03.xml"
			type="instance"/>
		<Include
			source="DATA:civilian/italy_it/props/itpdebris01.xml"
			type="instance"/>
		<Include
			source="DATA:civilian/italy_it/props/itpdebris03.xml"
			type="instance"/>
		<Include
			source="DATA:civilian/italy_it/props/itpdebris04.xml"
			type="instance"/>
		<Include
			source="DATA:civilian/italy_it/props/itpdebris05.xml"
			type="instance"/>
		<Include
			source="DATA:civilian/italy_it/rocks/itrocks01.xml"
			type="instance"/>
		<Include
			source="DATA:civilian/italy_it/rocks/itrocks02.xml"
			type="instance"/>
		<Include
			source="DATA:civilian/italy_it/rocks/itrocks03.xml"
			type="instance"/>
		<Include
			source="DATA:civilian/italy_it/rocks/itrocks04.xml"
			type="instance"/>
		<Include
			source="DATA:civilian/italy_it/rocks/itrocks06.xml"
			type="instance"/>
		<Include
			source="DATA:civilian/italy_it/rocks/itrocks08.xml"
			type="instance"/>
		<Include
			source="DATA:civilian/north_carolina_badlands_nc/buildings/ncbruin02.xml"
			type="instance"/>
		<Include
			source="DATA:civilian/props/rubble_titan02.xml"
			type="instance"/>
		<Include
			source="DATA:nod/structures_singleplayercampaign/nodrefineryspnoharvester.xml"
			type="instance"/>
		<Include
			source="DATA:sounds/musicscript_redzone.xml"
			type="instance"/>
		<Include
			source="overrides.xml"
			type="all"/>
	</Includes>
	<GameMap
		id="Commando_m02">
		<Waypoint
			id="Waypoint 18">
			<Position
				x="1356.54"
				y="3394.2"
				z="0"/>
		</Waypoint>
		<Waypoint
			id="Waypoint 17">
			<Position
				x="1741.94"
				y="638.486"
				z="0"/>
		</Waypoint>
		<Waypoint
			id="Waypoint 16">
			<Position
				x="1860.58"
				y="1091.88"
				z="0"/>
		</Waypoint>
		<Waypoint
			id="Waypoint 15">
			<Position
				x="1563.97"
				y="872.489"
				z="0"/>
		</Waypoint>
		<Waypoint
			id="Waypoint 14">
			<Position
				x="1729.52"
				y="863.296"
				z="0"/>
		</Waypoint>
		<Waypoint
			id="Waypoint 12">
			<Position
				x="1426.49"
				y="3501.79"
				z="0"/>
		</Waypoint>
		<Waypoint
			id="Waypoint 11">
			<Position
				x="1495.77"
				y="3327.41"
				z="0"/>
		</Waypoint>
		<Waypoint
			id="Waypoint 10">
			<Position
				x="1620.42"
				y="3209.7"
				z="0"/>
		</Waypoint>
		<Waypoint
			id="Waypoint 9">
			<Position
				x="1859.76"
				y="3333.72"
				z="0"/>
		</Waypoint>
		<Waypoint
			id="Waypoint 8">
			<Position
				x="1984.95"
				y="3514.25"
				z="0"/>
		</Waypoint>
		<Waypoint
			id="Waypoint 7">
			<Position
				x="1457.32"
				y="3439.5"
				z="0"/>
		</Waypoint>
		<Waypoint
			id="Waypoint 6">
			<Position
				x="1787.4"
				y="891.433"
				z="0"/>
		</Waypoint>
		<Waypoint
			id="Waypoint 5">
			<Position
				x="1584.22"
				y="2694.13"
				z="0"/>
		</Waypoint>
		<Waypoint
			id="Waypoint 4">
			<Position
				x="228.955"
				y="156.761"
				z="0"/>
		</Waypoint>
		<Waypoint
			id="InitialCameraPosition">
			<Position
				x="212.845"
				y="336.913"
				z="0"/>
		</Waypoint>
		<Waypoint
			id="Waypoint 2">
			<Position
				x="182.671"
				y="271.639"
				z="0"/>
		</Waypoint>
		<Waypoint
			id="Waypoint 1">
			<Position
				x="6.53742"
				y="275.575"
				z="0"/>
		</Waypoint>
		<Structure
			Angle="-0.785398"
			EventList=""
			Faction="NOD5/teamNOD5"
			Health="100"
			Team="NOD5"
			ThingTemplate="NODTiberiumSilo"
			id="NODTiberiumSilo">
			<Position
				x="547.539"
				y="3107.44"
				z="0"/>
		</Structure>
		<Structure
			Angle="2.6911"
			EventList=""
			Faction="NOD5/teamNOD5"
			Health="100"
			Team="NOD5"
			ThingTemplate="NODObelisk"
			id="NODObelisk">
			<Position
				x="804.459"
				y="3201.7"
				z="0"/>
		</Structure>
		<Structure
			Angle="-0.903644"
			EventList=""
			Faction="NOD5/teamNOD5"
			Health="100"
			Team="NOD5"
			ThingTemplate="NODDropZone"
			id="NODDropZone">
			<Position
				x="584.444"
				y="3559.06"
				z="0"/>
		</Structure>
		<Structure
			Angle="-0.785398"
			EventList=""
			Faction="NOD5/teamNOD5"
			Health="100"
			Team="NOD5"
			ThingTemplate="NODOperationsCenter"
			id="NODOperationsCenter">
			<Position
				x="683.595"
				y="3094.7"
				z="0"/>
		</Structure>
		<Structure
			Angle="0.785398"
			EventList=""
			Faction="NOD5/teamNOD5"
			Health="100"
			Team="NOD5"
			ThingTemplate="NODPowerPlant"
			id="NODPowerPlant">
			<Position
				x="323.76"
				y="3774.84"
				z="0"/>
		</Structure>
		<Structure
			Angle="0.785398"
			EventList=""
			Faction="NOD5/teamNOD5"
			Health="100"
			Team="NOD5"
			ThingTemplate="NODPowerPlant"
			id="NODPowerPlant">
			<Position
				x="236.198"
				y="3648.83"
				z="0"/>
		</Structure>
		<Structure
			Angle="0.785398"
			EventList=""
			Faction="NOD5/teamNOD5"
			Health="100"
			Team="NOD5"
			ThingTemplate="NODPowerPlant"
			id="NODPowerPlant">
			<Position
				x="242.169"
				y="3841.83"
				z="0"/>
		</Structure>
		<Structure
			Angle="0.785398"
			EventList=""
			Faction="NOD5/teamNOD5"
			Health="100"
			Team="NOD5"
			ThingTemplate="NODPowerPlant"
			id="NODPowerPlant">
			<Position
				x="137.314"
				y="3719.61"
				z="0"/>
		</Structure>
		<Structure
			Angle="-2.35619"
			EventList=""
			Faction="NOD5/teamNOD5"
			Health="100"
			Team="NOD5"
			ThingTemplate="NODTechAssemblyPlant"
			id="NODTechAssemblyPlant">
			<Position
				x="393.895"
				y="3571.82"
				z="0"/>
		</Structure>
		<Structure
			Angle="-0.785398"
			EventList=""
			Faction="NOD5/teamNOD5"
			Health="100"
			Team="NOD5"
			ThingTemplate="NODTiberiumSilo"
			id="NODTiberiumSilo">
			<Position
				x="625.354"
				y="3243.54"
				z="0"/>
		</Structure>
		<Structure
			Angle="-0.785398"
			EventList=""
			Faction="NOD5/teamNOD5"
			Health="100"
			Team="NOD5"
			ThingTemplate="NODTiberiumSilo"
			id="NODTiberiumSilo">
			<Position
				x="544.621"
				y="3256.2"
				z="0"/>
		</Structure>
		<Structure
			Angle="-2.38165"
			EventList=""
			Faction="NOD5/teamNOD5"
			Health="100"
			Team="NOD5"
			ThingTemplate="NODRefinerySPNoHarvester"
			id="NODRefinerySPNoHarvester">
			<Position
				x="465.958"
				y="3342.31"
				z="0"/>
		</Structure>
		<Structure
			Angle="2.1054"
			EventList=""
			Faction="NOD5/teamNOD5"
			Health="100"
			Team="NOD5"
			ThingTemplate="NODObelisk"
			id="NODObelisk">
			<Position
				x="326.848"
				y="3148.18"
				z="0"/>
		</Structure>
		<Structure
			Angle="2.6911"
			EventList=""
			Faction="NOD5/teamNOD5"
			Health="100"
			Team="NOD5"
			ThingTemplate="NODObelisk"
			id="NODObelisk">
			<Position
				x="910.624"
				y="3619.98"
				z="0"/>
		</Structure>
		<Structure
			Angle="-2.35619"
			EventList=""
			Faction="NOD5/teamNOD5"
			Health="100"
			Team="NOD5"
			ThingTemplate="NODCrane"
			id="NODCrane">
			<Position
				x="223.37"
				y="3430.85"
				z="0"/>
		</Structure>
		<Structure
			Angle="-0.785398"
			EventList=""
			Faction="NOD5/teamNOD5"
			Health="100"
			Team="NOD5"
			ThingTemplate="NODHandOfNOD"
			id="NODHandOfNOD">
			<Position
				x="763.938"
				y="3705.75"
				z="0"/>
		</Structure>
		<Structure
			Angle="2.29951"
			EventList=""
			Faction="NOD4/teamNOD4"
			Health="100"
			Team="NOD4"
			ThingTemplate="NODObelisk"
			id="NODObelisk">
			<Position
				x="1431.99"
				y="3210.67"
				z="0"/>
		</Structure>
		<Structure
			Angle="-0.0245"
			EventList=""
			Faction="NOD4/teamNOD4"
			Health="100"
			Team="NOD4"
			ThingTemplate="NODHandOfNOD"
			id="NODHandOfNOD">
			<Position
				x="1182.1"
				y="3303.73"
				z="0"/>
		</Structure>
		<Structure
			Angle="-0.0794421"
			EventList=""
			Faction="NOD4/teamNOD4"
			Health="100"
			Team="NOD4"
			ThingTemplate="NODHandOfNOD"
			id="NODHandOfNOD">
			<Position
				x="1236.43"
				y="3448.67"
				z="0"/>
		</Structure>
		<Structure
			Angle="-1.00329"
			EventList=""
			Faction="NOD4/teamNOD4"
			Health="100"
			Team="NOD4"
			ThingTemplate="NODDropZone"
			id="NODDropZone">
			<Position
				x="1219.54"
				y="3613.79"
				z="0"/>
		</Structure>
		<Structure
			Angle="-0.785398"
			EventList=""
			Faction="NOD4/teamNOD4"
			Health="100"
			Team="NOD4"
			ThingTemplate="NODOperationsCenter"
			id="NODOperationsCenter">
			<Position
				x="1392.5"
				y="3592.93"
				z="0"/>
		</Structure>
		<Structure
			Angle="0.785398"
			EventList=""
			Faction="NOD4/teamNOD4"
			Health="100"
			Team="NOD4"
			ThingTemplate="NODPowerPlant"
			id="NODPowerPlant">
			<Position
				x="1557.64"
				y="3609.9"
				z="0"/>
		</Structure>
		<Structure
			Angle="0.785398"
			EventList=""
			Faction="NOD4/teamNOD4"
			Health="100"
			Team="NOD4"
			ThingTemplate="NODPowerPlant"
			id="NODPowerPlant">
			<Position
				x="1640.22"
				y="3490.69"
				z="0"/>
		</Structure>
		<Structure
			Angle="2.21598"
			EventList=""
			Faction="player0001/teamplayer0001"
			Health="100"
			Team="player0001"
			ThingTemplate="RubbledBuilding03"
			id="RubbledBuilding03">
			<Position
				x="783.312"
				y="1026.38"
				z="0"/>
		</Structure>
		<Structure
			Angle="2.35507"
			EventList=""
			Faction="NODWALL/teamNODWALL"
			Health="100"
			Team="NODWALL"
			ThingTemplate="NODWallHub"
			id="NODWallHub">
			<Position
				x="1705.73"
				y="2956.3"
				z="0"/>
		</Structure>
		<Structure
			Angle="-1.37943"
			EventList=""
			Faction="NODWALL/teamNODWALL"
			Health="100"
			Team="NODWALL"
			ThingTemplate="NODWallSegment"
			id="NODWallSegment">
			<Position
				x="1612.56"
				y="2938.36"
				z="0"/>
		</Structure>
		<Structure
			Angle="-1.37943"
			EventList=""
			Faction="NODWALL/teamNODWALL"
			Health="100"
			Team="NODWALL"
			ThingTemplate="NODWallSegment"
			id="NODWallSegment">
			<Position
				x="1632.19"
				y="2942.09"
				z="0"/>
		</Structure>
		<Structure
			Angle="-1.37943"
			EventList=""
			Faction="NODWALL/teamNODWALL"
			Health="100"
			Team="NODWALL"
			ThingTemplate="NODWallSegment"
			id="NODWallSegment">
			<Position
				x="1651.71"
				y="2945.86"
				z="0"/>
		</Structure>
		<Structure
			Angle="-1.37943"
			EventList=""
			Faction="NODWALL/teamNODWALL"
			Health="100"
			Team="NODWALL"
			ThingTemplate="NODWallSegment"
			id="NODWallSegment">
			<Position
				x="1671.3"
				y="2949.59"
				z="0"/>
		</Structure>
		<Structure
			Angle="-1.37943"
			EventList=""
			Faction="NODWALL/teamNODWALL"
			Health="100"
			Team="NODWALL"
			ThingTemplate="NODWallSegment"
			id="NODWallSegment">
			<Position
				x="1690.92"
				y="2953.32"
				z="0"/>
		</Structure>
		<Structure
			Angle="2.35507"
			EventList=""
			Faction="NODWALL/teamNODWALL"
			Health="100"
			Team="NODWALL"
			ThingTemplate="NODWallHub"
			id="NODWallHub">
			<Position
				x="1595.53"
				y="2936.17"
				z="0"/>
		</Structure>
		<Structure
			Angle="-1.27188"
			EventList=""
			Faction="NODWALL/teamNODWALL"
			Health="100"
			Team="NODWALL"
			ThingTemplate="NODWallSegment"
			id="NODWallSegment">
			<Position
				x="1482.73"
				y="2903.35"
				z="0"/>
		</Structure>
		<Structure
			Angle="-1.27188"
			EventList=""
			Faction="NODWALL/teamNODWALL"
			Health="100"
			Team="NODWALL"
			ThingTemplate="NODWallSegment"
			id="NODWallSegment">
			<Position
				x="1501.85"
				y="2909.16"
				z="0"/>
		</Structure>
		<Structure
			Angle="-1.27188"
			EventList=""
			Faction="NODWALL/teamNODWALL"
			Health="100"
			Team="NODWALL"
			ThingTemplate="NODWallSegment"
			id="NODWallSegment">
			<Position
				x="1520.85"
				y="2915"
				z="0"/>
		</Structure>
		<Structure
			Angle="-1.27188"
			EventList=""
			Faction="NODWALL/teamNODWALL"
			Health="100"
			Team="NODWALL"
			ThingTemplate="NODWallSegment"
			id="NODWallSegment">
			<Position
				x="1539.92"
				y="2920.82"
				z="0"/>
		</Structure>
		<Structure
			Angle="-1.27188"
			EventList=""
			Faction="NODWALL/teamNODWALL"
			Health="100"
			Team="NODWALL"
			ThingTemplate="NODWallSegment"
			id="NODWallSegment">
			<Position
				x="1559.04"
				y="2926.63"
				z="0"/>
		</Structure>
		<Structure
			Angle="2.46263"
			EventList=""
			Faction="NODWALL/teamNODWALL"
			Health="100"
			Team="NODWALL"
			ThingTemplate="NODWallHub"
			id="NODWallHub">
			<Position
				x="1466.04"
				y="2899.34"
				z="0"/>
		</Structure>
		<Structure
			Angle="-1.27188"
			EventList=""
			Faction="NODWALL/teamNODWALL"
			Health="100"
			Team="NODWALL"
			ThingTemplate="NODWallSegment"
			id="NODWallSegment">
			<Position
				x="1578.04"
				y="2932.47"
				z="0"/>
		</Structure>
		<Structure
			Angle="-0.877668"
			EventList=""
			Faction="NODWALL/teamNODWALL"
			Health="100"
			Team="NODWALL"
			ThingTemplate="NODWallSegment"
			id="NODWallSegment">
			<Position
				x="1375.54"
				y="2829.46"
				z="0"/>
		</Structure>
		<Structure
			Angle="-0.877668"
			EventList=""
			Faction="NODWALL/teamNODWALL"
			Health="100"
			Team="NODWALL"
			ThingTemplate="NODWallSegment"
			id="NODWallSegment">
			<Position
				x="1390.96"
				y="2842.16"
				z="0"/>
		</Structure>
		<Structure
			Angle="-0.877668"
			EventList=""
			Faction="NODWALL/teamNODWALL"
			Health="100"
			Team="NODWALL"
			ThingTemplate="NODWallSegment"
			id="NODWallSegment">
			<Position
				x="1406.26"
				y="2854.86"
				z="0"/>
		</Structure>
		<Structure
			Angle="-0.877668"
			EventList=""
			Faction="NODWALL/teamNODWALL"
			Health="100"
			Team="NODWALL"
			ThingTemplate="NODWallSegment"
			id="NODWallSegment">
			<Position
				x="1421.64"
				y="2867.55"
				z="0"/>
		</Structure>
		<Structure
			Angle="-0.877668"
			EventList=""
			Faction="NODWALL/teamNODWALL"
			Health="100"
			Team="NODWALL"
			ThingTemplate="NODWallSegment"
			id="NODWallSegment">
			<Position
				x="1437.05"
				y="2880.26"
				z="0"/>
		</Structure>
		<Structure
			Angle="2.85684"
			EventList=""
			Faction="NODWALL/teamNODWALL"
			Health="100"
			Team="NODWALL"
			ThingTemplate="NODWallHub"
			id="NODWallHub">
			<Position
				x="1361.67"
				y="2819.34"
				z="0"/>
		</Structure>
		<Structure
			Angle="-0.877668"
			EventList=""
			Faction="NODWALL/teamNODWALL"
			Health="100"
			Team="NODWALL"
			ThingTemplate="NODWallSegment"
			id="NODWallSegment">
			<Position
				x="1452.35"
				y="2892.95"
				z="0"/>
		</Structure>
		<Structure
			Angle="-2.35619"
			EventList=""
			Faction="NODWALL/teamNODWALL"
			Health="100"
			Team="NODWALL"
			ThingTemplate="NODWallHub"
			id="NODWallHub">
			<Position
				x="1405.13"
				y="2566.59"
				z="0"/>
		</Structure>
		<Structure
			Angle="0.192486"
			EventList=""
			Faction="NODWALL/teamNODWALL"
			Health="100"
			Team="NODWALL"
			ThingTemplate="NODWallSegment"
			id="NODWallSegment">
			<Position
				x="1425.36"
				y="2456.53"
				z="0"/>
		</Structure>
		<Structure
			Angle="0.192486"
			EventList=""
			Faction="NODWALL/teamNODWALL"
			Health="100"
			Team="NODWALL"
			ThingTemplate="NODWallSegment"
			id="NODWallSegment">
			<Position
				x="1421.62"
				y="2476.16"
				z="0"/>
		</Structure>
		<Structure
			Angle="0.192486"
			EventList=""
			Faction="NODWALL/teamNODWALL"
			Health="100"
			Team="NODWALL"
			ThingTemplate="NODWallSegment"
			id="NODWallSegment">
			<Position
				x="1417.83"
				y="2495.67"
				z="0"/>
		</Structure>
		<Structure
			Angle="0.192486"
			EventList=""
			Faction="NODWALL/teamNODWALL"
			Health="100"
			Team="NODWALL"
			ThingTemplate="NODWallSegment"
			id="NODWallSegment">
			<Position
				x="1414.07"
				y="2515.25"
				z="0"/>
		</Structure>
		<Structure
			Angle="0.192486"
			EventList=""
			Faction="NODWALL/teamNODWALL"
			Health="100"
			Team="NODWALL"
			ThingTemplate="NODWallSegment"
			id="NODWallSegment">
			<Position
				x="1410.32"
				y="2534.88"
				z="0"/>
		</Structure>
		<Structure
			Angle="-2.35619"
			EventList=""
			Faction="NODWALL/teamNODWALL"
			Health="100"
			Team="NODWALL"
			ThingTemplate="NODWallHub"
			id="NODWallHub">
			<Position
				x="1427.58"
				y="2439.5"
				z="0"/>
		</Structure>
		<Structure
			Angle="0.192486"
			EventList=""
			Faction="NODWALL/teamNODWALL"
			Health="100"
			Team="NODWALL"
			ThingTemplate="NODWallSegment"
			id="NODWallSegment">
			<Position
				x="1406.53"
				y="2554.39"
				z="0"/>
		</Structure>
		<Structure
			Angle="-2.43809"
			EventList=""
			Faction="NOD2/teamNOD2"
			Health="100"
			Team="NOD2"
			ThingTemplate="NODHandOfNOD"
			id="NODHandOfNOD">
			<Position
				x="1598.06"
				y="2827.01"
				z="0"/>
		</Structure>
		<Structure
			Angle="0.158744"
			EventList=""
			Faction="NOD2/teamNOD2"
			Health="100"
			Team="NOD2"
			ThingTemplate="NODDropZone"
			id="NODDropZone">
			<Position
				x="1551.23"
				y="2583.65"
				z="0"/>
		</Structure>
		<Structure
			Angle="-0.785398"
			EventList=""
			Faction="NOD2/teamNOD2"
			Health="100"
			Team="NOD2"
			ThingTemplate="NODOperationsCenter"
			id="NODOperationsCenter">
			<Position
				x="1730.17"
				y="2849.64"
				z="0"/>
		</Structure>
		<Structure
			Angle="0.0892212"
			EventList=""
			Faction="NOD2/teamNOD2"
			Health="100"
			Team="NOD2"
			ThingTemplate="NODObelisk"
			id="NODObelisk">
			<Position
				x="1385.86"
				y="2687.19"
				z="0"/>
		</Structure>
		<Structure
			Angle="0.785398"
			EventList=""
			Faction="NOD2/teamNOD2"
			Health="100"
			Team="NOD2"
			ThingTemplate="NODPowerPlant"
			id="NODPowerPlant">
			<Position
				x="1828.63"
				y="2734.72"
				z="0"/>
		</Structure>
		<Structure
			Angle="0.785398"
			EventList=""
			Faction="NOD2/teamNOD2"
			Health="100"
			Team="NOD2"
			ThingTemplate="NODPowerPlant"
			id="NODPowerPlant">
			<Position
				x="1782.62"
				y="2606.9"
				z="0"/>
		</Structure>
		<Structure
			Angle="0"
			EventList=""
			Faction="player0001/teamplayer0001"
			Health="100"
			Team="player0001"
			ThingTemplate="Italian_Ruin_19"
			id="Italian_Ruin_19">
			<Position
				x="1427.37"
				y="1709.15"
				z="0"/>
		</Structure>
		<Structure
			Angle="-1.84565"
			EventList=""
			Faction="player0001/teamplayer0001"
			Health="100"
			Team="player0001"
			ThingTemplate="Italian_Ruin_21"
			id="Italian_Ruin_21">
			<Position
				x="1223.57"
				y="1683.4"
				z="0"/>
		</Structure>
		<Structure
			Angle="-2.58175"
			EventList=""
			Faction="player0001/teamplayer0001"
			Health="100"
			Team="player0001"
			ThingTemplate="Italian_Ruin_22"
			id="Italian_Ruin_22">
			<Position
				x="1132.3"
				y="1532.01"
				z="0"/>
		</Structure>
		<Structure
			Angle="0"
			EventList=""
			Faction="player0001/teamplayer0001"
			Health="100"
			Team="player0001"
			ThingTemplate="Italian_Ruin_23"
			id="Italian_Ruin_23">
			<Position
				x="1249.73"
				y="1499.71"
				z="0"/>
		</Structure>
		<Structure
			Angle="0"
			EventList=""
			Faction="player0001/teamplayer0001"
			Health="100"
			Team="player0001"
			ThingTemplate="Italian_Ruin_25"
			id="Italian_Ruin_25">
			<Position
				x="1185.15"
				y="1470.84"
				z="0"/>
		</Structure>
		<Structure
			Angle="-1.32255"
			EventList=""
			Faction="player0001/teamplayer0001"
			Health="100"
			Team="player0001"
			ThingTemplate="North_Carolina_Ruin_02"
			id="North_Carolina_Ruin_02">
			<Position
				x="1365.8"
				y="1440.25"
				z="0"/>
		</Structure>
		<Structure
			Angle="-2.89619"
			EventList=""
			Faction="player0001/teamplayer0001"
			Health="100"
			Team="player0001"
			ThingTemplate="RubbledBuilding04"
			id="RubbledBuilding04">
			<Position
				x="1423.05"
				y="1621.2"
				z="0"/>
		</Structure>
		<Structure
			Angle="-3.11303"
			EventList=""
			Faction="player0001/teamplayer0001"
			Health="100"
			Team="player0001"
			ThingTemplate="RubbledBuilding03"
			id="RubbledBuilding03">
			<Position
				x="1257.67"
				y="1473.71"
				z="0"/>
		</Structure>
		<Structure
			Angle="-2.25347"
			EventList=""
			Faction="player0001/teamplayer0001"
			Health="100"
			Team="player0001"
			ThingTemplate="RubbledBuilding02"
			id="RubbledBuilding02">
			<Position
				x="1231.33"
				y="1584.03"
				z="0"/>
		</Structure>
		<Structure
			Angle="0.773483"
			EventList=""
			Faction="NOD/teamNOD"
			Health="100"
			Team="NOD"
			ThingTemplate="NODPowerPlant"
			id="NODPowerPlant">
			<Position
				x="1834.17"
				y="938.179"
				z="0"/>
		</Structure>
		<Structure
			Angle="0.785398"
			EventList=""
			Faction="NOD/teamNOD"
			Health="100"
			Team="NOD"
			ThingTemplate="NODPowerPlant"
			id="NODPowerPlant">
			<Position
				x="1722.08"
				y="918.48"
				z="0"/>
		</Structure>
		<Structure
			Angle="-2.13829"
			EventList=""
			Faction="NOD/teamNOD"
			Health="100"
			Team="NOD"
			ThingTemplate="NODHandOfNOD"
			id="NODHandOfNOD">
			<Position
				x="1756.2"
				y="802.91"
				z="0"/>
		</Structure>
		<Structure
			Angle="2.98409"
			EventList=""
			Faction="player0001/teamplayer0001"
			Health="100"
			Team="player0001"
			ThingTemplate="Italian_Ruin_22"
			id="Italian_Ruin_22">
			<Position
				x="627.847"
				y="689.655"
				z="0"/>
		</Structure>
		<Structure
			Angle="0.499604"
			EventList=""
			Faction="player0001/teamplayer0001"
			Health="100"
			Team="player0001"
			ThingTemplate="ITBRui29"
			id="ITBRUI29">
			<Position
				x="670.521"
				y="822.13"
				z="0"/>
		</Structure>
		<Structure
			Angle="-1.15212"
			EventList=""
			Faction="player0001/teamplayer0001"
			Health="100"
			Team="player0001"
			ThingTemplate="Italian_Ruin_24"
			id="Italian_Ruin_24">
			<Position
				x="831.145"
				y="697.578"
				z="0"/>
		</Structure>
		<Structure
			Angle="0"
			EventList=""
			Faction="player0001/teamplayer0001"
			Health="100"
			Team="player0001"
			ThingTemplate="Italian_Ruin_23"
			id="Italian_Ruin_23">
			<Position
				x="635.901"
				y="602.879"
				z="0"/>
		</Structure>
		<Structure
			Angle="-2.782"
			EventList=""
			Faction="player0001/teamplayer0001"
			Health="100"
			Team="player0001"
			ThingTemplate="Italian_Ruin_21"
			id="Italian_Ruin_21">
			<Position
				x="670.625"
				y="594.501"
				z="0"/>
		</Structure>
		<Unit
			Angle="-0.280268"
			EventList=""
			Faction="NOD4/teamNOD4"
			Health="100"
			Team="NOD4"
			ThingTemplate="NODMilitantSquad"
			id="NODMilitantSquad">
			<Position
				x="766.056"
				y="3510.95"
				z="0"/>
		</Unit>
		<Unit
			Angle="-0.264182"
			EventList=""
			Faction="NOD3/teamNOD3"
			Health="100"
			Team="NOD3"
			ThingTemplate="NODRaiderTank"
			id="NODRaiderTank">
			<Position
				x="1011.26"
				y="3500.2"
				z="0"/>
		</Unit>
		<Unit
			Angle="-2.6443"
			EventList=""
			Faction="NOD5/teamNOD5"
			Health="100"
			Team="NOD5"
			ThingTemplate="NODHarvester"
			id="NODHarvester">
			<Position
				x="198.638"
				y="3271.84"
				z="0"/>
		</Unit>
		<Unit
			Angle="-0.981601"
			EventList=""
			Faction="NOD5/teamNOD5"
			Health="100"
			Team="NOD5"
			ThingTemplate="NODHarvester"
			id="NODHarvester">
			<Position
				x="148.36"
				y="2535.31"
				z="0"/>
		</Unit>
		<Unit
			Angle="-0.264182"
			EventList=""
			Faction="NOD3/teamNOD3"
			Health="100"
			Team="NOD3"
			ThingTemplate="NODRaiderTank"
			id="NODRaiderTank">
			<Position
				x="1011.99"
				y="3452.25"
				z="0"/>
		</Unit>
		<Unit
			Angle="-0.264182"
			EventList=""
			Faction="NOD3/teamNOD3"
			Health="100"
			Team="NOD3"
			ThingTemplate="NODRaiderTank"
			id="NODRaiderTank">
			<Position
				x="1140.25"
				y="3415.15"
				z="0"/>
		</Unit>
		<Unit
			Angle="-0.657517"
			EventList=""
			Faction="NOD3/teamNOD3"
			Health="100"
			Team="NOD3"
			ThingTemplate="NODRaiderTank"
			id="NODRaiderTank">
			<Position
				x="1270.81"
				y="3522.87"
				z="0"/>
		</Unit>
		<Unit
			Angle="-0.264182"
			EventList=""
			Faction="NOD3/teamNOD3"
			Health="100"
			Team="NOD3"
			ThingTemplate="NODRaiderTank"
			id="NODRaiderTank">
			<Position
				x="1218.47"
				y="3386.65"
				z="0"/>
		</Unit>
		<Unit
			Angle="-0.132388"
			EventList=""
			Faction="NOD3/teamNOD3"
			Health="100"
			Team="NOD3"
			ThingTemplate="NODMilitantSquad"
			id="NODMilitantSquad">
			<Position
				x="1313.99"
				y="3202.9"
				z="0"/>
		</Unit>
		<Unit
			Angle="-0.0584156"
			EventList=""
			Faction="NOD3/teamNOD3"
			Health="100"
			Team="NOD3"
			ThingTemplate="NODMilitantSquad"
			id="NODMilitantSquad">
			<Position
				x="1371.99"
				y="3329.34"
				z="0"/>
		</Unit>
		<Unit
			Angle="-1.10317"
			EventList=""
			Faction="NOD3/teamNOD3"
			Health="100"
			Team="NOD3"
			ThingTemplate="NODMilitantSquad"
			id="NODMilitantSquad">
			<Position
				x="1507.56"
				y="3389.9"
				z="0"/>
		</Unit>
		<Unit
			Angle="-1.61398"
			EventList=""
			Faction="NOD3/teamNOD3"
			Health="100"
			Team="NOD3"
			ThingTemplate="NODMilitantSquad"
			id="NODMilitantSquad">
			<Position
				x="1532.33"
				y="1706.46"
				z="0"/>
		</Unit>
		<Unit
			Angle="-1.61398"
			EventList=""
			Faction="NOD3/teamNOD3"
			Health="100"
			Team="NOD3"
			ThingTemplate="NODMilitantSquad"
			id="NODMilitantSquad">
			<Position
				x="1731.51"
				y="1731.29"
				z="0"/>
		</Unit>
		<Unit
			Angle="0"
			EventList=""
			Faction="PLAYER/teamPLAYER"
			Health="100"
			Team="PLAYER"
			ThingTemplate="GenericRadarSupplier"
			id="GenericRadarSupplier">
			<Position
				x="273.351"
				y="205.812"
				z="0"/>
		</Unit>
		<Unit
			Angle="-1.95991"
			EventList=""
			Faction="NOD/teamNOD"
			Health="100"
			Team="NOD"
			ThingTemplate="NODMilitantSquad"
			id="NODMilitantSquad">
			<Position
				x="971.933"
				y="698.955"
				z="0"/>
		</Unit>
		<Unit
			Angle="-2.72077"
			EventList=""
			Faction="NOD/teamNOD"
			Health="100"
			Team="NOD"
			ThingTemplate="NODMilitantSquad"
			id="NODMilitantSquad">
			<Position
				x="911.229"
				y="583.324"
				z="0"/>
		</Unit>
		<Unit
			Angle="-2.84092"
			EventList=""
			Faction="NOD2/teamNOD2"
			Health="100"
			Team="NOD2"
			ThingTemplate="NODMilitantSquad"
			id="NODMilitantSquad">
			<Position
				x="1336.49"
				y="2645.09"
				z="0"/>
		</Unit>
		<Unit
			Angle="-2.35899"
			EventList=""
			Faction="NOD2/teamNOD2"
			Health="100"
			Team="NOD2"
			ThingTemplate="NODMilitantRocketSquad"
			id="NODMilitantRocketSquad">
			<Position
				x="1469.23"
				y="2689.14"
				z="0"/>
		</Unit>
		<Unit
			Angle="-3.11758"
			EventList=""
			Faction="NOD2/teamNOD2"
			Health="100"
			Team="NOD2"
			ThingTemplate="NODMilitantRocketSquad"
			id="NODMilitantRocketSquad">
			<Position
				x="1644.76"
				y="2718.47"
				z="0"/>
		</Unit>
		<Unit
			Angle="3.14159"
			EventList=""
			Faction="NOD2/teamNOD2"
			Health="100"
			Team="NOD2"
			ThingTemplate="NODBlackHandSquad"
			id="NODBlackHandSquad">
			<Position
				x="1522.73"
				y="2823.96"
				z="0"/>
		</Unit>
		<Unit
			Angle="-1.3351"
			EventList=""
			Faction="NOD/teamNOD"
			Health="100"
			Team="NOD"
			ThingTemplate="NODBlackHandSquad"
			id="NODBlackHandSquad">
			<Position
				x="723.456"
				y="704.194"
				z="0"/>
		</Unit>
		<Unit
			Angle="-2.14382"
			EventList=""
			Faction="NOD/teamNOD"
			Health="100"
			Team="NOD"
			ThingTemplate="NODMilitantSquad"
			id="NODMilitantSquad">
			<Position
				x="772.395"
				y="612.929"
				z="0"/>
		</Unit>
		<Unit
			Angle="-2.75642"
			EventList=""
			Faction="NOD/teamNOD"
			Health="100"
			Team="NOD"
			ThingTemplate="NODBlackHandSquad"
			id="NODBlackHandSquad">
			<Position
				x="1810.18"
				y="706.295"
				z="0"/>
		</Unit>
		<Unit
			Angle="-2.4718"
			EventList=""
			Faction="NOD/teamNOD"
			Health="100"
			Team="NOD"
			ThingTemplate="NODMilitantRocketSquad"
			id="NODMilitantRocketSquad">
			<Position
				x="1698.82"
				y="831.055"
				z="0"/>
		</Unit>
		<Unit
			Angle="-2.32784"
			EventList=""
			Faction="NOD/teamNOD"
			Health="100"
			Team="NOD"
			ThingTemplate="NODMilitantSquad"
			id="NODMilitantSquad">
			<Position
				x="1723.95"
				y="742.003"
				z="0"/>
		</Unit>
		<Prop
			Angle="1.18627"
			EventList=""
			Faction="player0001/teamplayer0001"
			Health="100"
			Team="player0001"
			ThingTemplate="ASTdead02a"
			id="ASTDEAD02A">
			<Position
				x="801.927"
				y="1426.28"
				z="0"/>
		</Prop>
		<Prop
			Angle="-0.836504"
			EventList=""
			Faction="player0001/teamplayer0001"
			Health="100"
			Team="player0001"
			ThingTemplate="ASTdead02"
			id="ASTDEAD02">
			<Position
				x="816.928"
				y="1410.66"
				z="0"/>
		</Prop>
		<Prop
			Angle="0.717688"
			EventList=""
			Faction="player0001/teamplayer0001"
			Health="100"
			Team="player0001"
			ThingTemplate="ASTdead02"
			id="ASTDEAD02">
			<Position
				x="901.699"
				y="1402.11"
				z="0"/>
		</Prop>
		<Prop
			Angle="-2.49124"
			EventList=""
			Faction="player0001/teamplayer0001"
			Health="100"
			Team="player0001"
			ThingTemplate="ASTdead03"
			id="ASTdead03">
			<Position
				x="851.745"
				y="1402.22"
				z="0"/>
		</Prop>
		<Prop
			Angle="-2.49124"
			EventList=""
			Faction="player0001/teamplayer0001"
			Health="100"
			Team="player0001"
			ThingTemplate="ASTdead02a"
			id="ASTDEAD02A">
			<Position
				x="891.579"
				y="1390.45"
				z="0"/>
		</Prop>
		<Prop
			Angle="-2.60568"
			EventList=""
			Faction="player0001/teamplayer0001"
			Health="100"
			Team="player0001"
			ThingTemplate="ASTdead02a"
			id="ASTDEAD02A">
			<Position
				x="491.004"
				y="2559.27"
				z="0"/>
		</Prop>
		<Prop
			Angle="1.65473"
			EventList=""
			Faction="player0001/teamplayer0001"
			Health="100"
			Team="player0001"
			ThingTemplate="ASTdead02"
			id="ASTDEAD02">
			<Position
				x="469.632"
				y="2572.78"
				z="0"/>
		</Prop>
		<Prop
			Angle="-3.07426"
			EventList=""
			Faction="player0001/teamplayer0001"
			Health="100"
			Team="player0001"
			ThingTemplate="ASTdead02"
			id="ASTDEAD02">
			<Position
				x="407.342"
				y="2630.92"
				z="0"/>
		</Prop>
		<Prop
			Angle="0"
			EventList=""
			Faction="player0001/teamplayer0001"
			Health="100"
			Team="player0001"
			ThingTemplate="ASTdead03"
			id="ASTdead03">
			<Position
				x="447.035"
				y="2600.59"
				z="0"/>
		</Prop>
		<Prop
			Angle="0"
			EventList=""
			Faction="player0001/teamplayer0001"
			Health="100"
			Team="player0001"
			ThingTemplate="ASTdead02a"
			id="ASTDEAD02A">
			<Position
				x="422.455"
				y="2634.07"
				z="0"/>
		</Prop>
		<Prop
			Angle="2.14472"
			EventList=""
			Faction="player0001/teamplayer0001"
			Health="100"
			Team="player0001"
			ThingTemplate="ASTdead02a"
			id="ASTDEAD02A">
			<Position
				x="1034.87"
				y="2782.46"
				z="0"/>
		</Prop>
		<Prop
			Angle="0.12194"
			EventList=""
			Faction="player0001/teamplayer0001"
			Health="100"
			Team="player0001"
			ThingTemplate="ASTdead02"
			id="ASTDEAD02">
			<Position
				x="1047.56"
				y="2804.33"
				z="0"/>
		</Prop>
		<Prop
			Angle="1.67613"
			EventList=""
			Faction="player0001/teamplayer0001"
			Health="100"
			Team="player0001"
			ThingTemplate="ASTdead02"
			id="ASTDEAD02">
			<Position
				x="1103.28"
				y="2868.78"
				z="0"/>
		</Prop>
		<Prop
			Angle="-1.53279"
			EventList=""
			Faction="player0001/teamplayer0001"
			Health="100"
			Team="player0001"
			ThingTemplate="ASTdead03"
			id="ASTdead03">
			<Position
				x="1074.48"
				y="2827.96"
				z="0"/>
		</Prop>
		<Prop
			Angle="-1.53279"
			EventList=""
			Faction="player0001/teamplayer0001"
			Health="100"
			Team="player0001"
			ThingTemplate="ASTdead02a"
			id="ASTDEAD02A">
			<Position
				x="1107"
				y="2853.8"
				z="0"/>
		</Prop>
		<Prop
			Angle="-2.38385"
			EventList=""
			Faction="player0001/teamplayer0001"
			Health="100"
			Team="player0001"
			ThingTemplate="ASTdead02a"
			id="ASTDEAD02A">
			<Position
				x="2012.36"
				y="2709.98"
				z="0"/>
		</Prop>
		<Prop
			Angle="1.87656"
			EventList=""
			Faction="player0001/teamplayer0001"
			Health="100"
			Team="player0001"
			ThingTemplate="ASTdead02"
			id="ASTDEAD02">
			<Position
				x="1988.54"
				y="2718.45"
				z="0"/>
		</Prop>
		<Prop
			Angle="-2.85244"
			EventList=""
			Faction="player0001/teamplayer0001"
			Health="100"
			Team="player0001"
			ThingTemplate="ASTdead02"
			id="ASTDEAD02">
			<Position
				x="1914.99"
				y="2761.46"
				z="0"/>
		</Prop>
		<Prop
			Angle="0.221823"
			EventList=""
			Faction="player0001/teamplayer0001"
			Health="100"
			Team="player0001"
			ThingTemplate="ASTdead03"
			id="ASTdead03">
			<Position
				x="1960.38"
				y="2740.6"
				z="0"/>
		</Prop>
		<Prop
			Angle="0.221823"
			EventList=""
			Faction="player0001/teamplayer0001"
			Health="100"
			Team="player0001"
			ThingTemplate="ASTdead02a"
			id="ASTDEAD02A">
			<Position
				x="1929.04"
				y="2767.86"
				z="0"/>
		</Prop>
		<Prop
			Angle="-2.60568"
			EventList=""
			Faction="player0001/teamplayer0001"
			Health="100"
			Team="player0001"
			ThingTemplate="ASTdead02a"
			id="ASTDEAD02A">
			<Position
				x="1547.9"
				y="1844.87"
				z="0"/>
		</Prop>
		<Prop
			Angle="1.65473"
			EventList=""
			Faction="player0001/teamplayer0001"
			Health="100"
			Team="player0001"
			ThingTemplate="ASTdead02"
			id="ASTDEAD02">
			<Position
				x="1526.53"
				y="1858.38"
				z="0"/>
		</Prop>
		<Prop
			Angle="1.04981"
			EventList=""
			Faction="player0001/teamplayer0001"
			Health="100"
			Team="player0001"
			ThingTemplate="ASTdead06"
			id="ASTDEAD06">
			<Position
				x="1487.45"
				y="1846.46"
				z="0"/>
		</Prop>
		<Prop
			Angle="-3.07426"
			EventList=""
			Faction="player0001/teamplayer0001"
			Health="100"
			Team="player0001"
			ThingTemplate="ASTdead02"
			id="ASTDEAD02">
			<Position
				x="1464.24"
				y="1916.51"
				z="0"/>
		</Prop>
		<Prop
			Angle="0"
			EventList=""
			Faction="player0001/teamplayer0001"
			Health="100"
			Team="player0001"
			ThingTemplate="ASTdead03"
			id="ASTdead03">
			<Position
				x="1503.93"
				y="1886.18"
				z="0"/>
		</Prop>
		<Prop
			Angle="0"
			EventList=""
			Faction="player0001/teamplayer0001"
			Health="100"
			Team="player0001"
			ThingTemplate="ASTdead02a"
			id="ASTDEAD02A">
			<Position
				x="1479.35"
				y="1919.66"
				z="0"/>
		</Prop>
		<Prop
			Angle="0"
			EventList=""
			Faction="player0001/teamplayer0001"
			Health="100"
			Team="player0001"
			ThingTemplate="ITPDeadP01"
			id="ITPDEADP01">
			<Position
				x="1206.8"
				y="2680.85"
				z="0"/>
		</Prop>
		<Prop
			Angle="-1.7002"
			EventList=""
			Faction="player0001/teamplayer0001"
			Health="100"
			Team="player0001"
			ThingTemplate="ITPDeadP03"
			id="ITPDEADP03">
			<Position
				x="1248.24"
				y="2392.15"
				z="0"/>
		</Prop>
		<Prop
			Angle="0"
			EventList=""
			Faction="player0001/teamplayer0001"
			Health="100"
			Team="player0001"
			ThingTemplate="ITPDeadP03"
			id="ITPDEADP03">
			<Position
				x="799.651"
				y="1894.38"
				z="0"/>
		</Prop>
		<Prop
			Angle="-1.27091"
			EventList=""
			Faction="player0001/teamplayer0001"
			Health="100"
			Team="player0001"
			ThingTemplate="ITRocks02"
			id="ITROCKS02">
			<Position
				x="1243.14"
				y="2139.7"
				z="0"/>
		</Prop>
		<Prop
			Angle="-1.27091"
			EventList=""
			Faction="player0001/teamplayer0001"
			Health="100"
			Team="player0001"
			ThingTemplate="ITRocks02"
			id="ITROCKS02">
			<Position
				x="45.0421"
				y="666.14"
				z="0"/>
		</Prop>
		<Prop
			Angle="-1.27091"
			EventList=""
			Faction="player0001/teamplayer0001"
			Health="100"
			Team="player0001"
			ThingTemplate="ITRocks02"
			id="ITROCKS02">
			<Position
				x="162.204"
				y="999.982"
				z="0"/>
		</Prop>
		<Prop
			Angle="-0.640727"
			EventList=""
			Faction="player0001/teamplayer0001"
			Health="100"
			Team="player0001"
			ThingTemplate="ITRocks02"
			id="ITROCKS02">
			<Position
				x="1348.23"
				y="2292.04"
				z="0"/>
		</Prop>
		<Prop
			Angle="1.1153"
			EventList=""
			Faction="player0001/teamplayer0001"
			Health="100"
			Team="player0001"
			ThingTemplate="ITRocks02"
			id="ITROCKS02">
			<Position
				x="478.518"
				y="3161.18"
				z="0"/>
		</Prop>
		<Prop
			Angle="-1.27091"
			EventList=""
			Faction="player0001/teamplayer0001"
			Health="100"
			Team="player0001"
			ThingTemplate="ITRocks02"
			id="ITROCKS02">
			<Position
				x="675.139"
				y="2972.75"
				z="0"/>
		</Prop>
		<Prop
			Angle="-1.27091"
			EventList=""
			Faction="player0001/teamplayer0001"
			Health="100"
			Team="player0001"
			ThingTemplate="ITRocks02"
			id="ITROCKS02">
			<Position
				x="847.826"
				y="2771.84"
				z="0"/>
		</Prop>
		<Prop
			Angle="-1.27091"
			EventList=""
			Faction="player0001/teamplayer0001"
			Health="100"
			Team="player0001"
			ThingTemplate="ITRocks02"
			id="ITROCKS02">
			<Position
				x="1306.6"
				y="3779.36"
				z="0"/>
		</Prop>
		<Prop
			Angle="-1.44449"
			EventList=""
			Faction="player0001/teamplayer0001"
			Health="100"
			Team="player0001"
			ThingTemplate="ITRocks02"
			id="ITROCKS02">
			<Position
				x="1684.28"
				y="3946.49"
				z="0"/>
		</Prop>
		<Prop
			Angle="-1.27091"
			EventList=""
			Faction="player0001/teamplayer0001"
			Health="100"
			Team="player0001"
			ThingTemplate="ITRocks02"
			id="ITROCKS02">
			<Position
				x="1924.02"
				y="3755.74"
				z="0"/>
		</Prop>
		<Prop
			Angle="-0.459646"
			EventList=""
			Faction="player0001/teamplayer0001"
			Health="100"
			Team="player0001"
			ThingTemplate="ITRocks02"
			id="ITROCKS02">
			<Position
				x="1901.61"
				y="3891.58"
				z="0"/>
		</Prop>
		<Prop
			Angle="0"
			EventList=""
			Faction="PlyrNeutral/teamPlyrNeutral"
			Health="100"
			Team="PlyrNeutral"
			ThingTemplate="TiberiumField"
			id="TiberiumField">
			<Position
				x="542.241"
				y="2140.85"
				z="0"/>
		</Prop>
		<Prop
			Angle="0"
			EventList=""
			Faction="PlyrNeutral/teamPlyrNeutral"
			Health="100"
			Team="PlyrNeutral"
			ThingTemplate="TiberiumField"
			id="TiberiumField">
			<Position
				x="445.671"
				y="1898.03"
				z="0"/>
		</Prop>
		<Prop
			Angle="0"
			EventList=""
			Faction="PlyrNeutral/teamPlyrNeutral"
			Health="100"
			Team="PlyrNeutral"
			ThingTemplate="TiberiumField"
			id="TiberiumField">
			<Position
				x="196.919"
				y="2278.04"
				z="0"/>
		</Prop>
		<Prop
			Angle="0"
			EventList=""
			Faction="player0001/teamplayer0001"
			Health="100"
			Team="player0001"
			ThingTemplate="ASTdead01"
			id="ASTdead01">
			<Position
				x="1818.94"
				y="3451.87"
				z="0"/>
		</Prop>
		<Prop
			Angle="0.626159"
			EventList=""
			Faction="player0001/teamplayer0001"
			Health="100"
			Team="player0001"
			ThingTemplate="ASTdead02a"
			id="ASTDEAD02A">
			<Position
				x="1799.78"
				y="3439.31"
				z="0"/>
		</Prop>
		<Prop
			Angle="0"
			EventList=""
			Faction="player0001/teamplayer0001"
			Health="100"
			Team="player0001"
			ThingTemplate="ASTshrub01"
			id="ASTshrub01">
			<Position
				x="1774.85"
				y="3354.28"
				z="0"/>
		</Prop>
		<Prop
			Angle="2.44454"
			EventList=""
			Faction="player0001/teamplayer0001"
			Health="100"
			Team="player0001"
			ThingTemplate="ASTdead05"
			id="ASTDEAD05">
			<Position
				x="1802.32"
				y="3370.88"
				z="0"/>
		</Prop>
		<Prop
			Angle="0"
			EventList=""
			Faction="player0001/teamplayer0001"
			Health="100"
			Team="player0001"
			ThingTemplate="ASTdead05"
			id="ASTDEAD05">
			<Position
				x="1754.82"
				y="3312.56"
				z="0"/>
		</Prop>
		<Prop
			Angle="2.95355"
			EventList=""
			Faction="player0001/teamplayer0001"
			Health="100"
			Team="player0001"
			ThingTemplate="ASTdead04"
			id="ASTDEAD04">
			<Position
				x="1774.01"
				y="3361.31"
				z="0"/>
		</Prop>
		<Prop
			Angle="0.626159"
			EventList=""
			Faction="player0001/teamplayer0001"
			Health="100"
			Team="player0001"
			ThingTemplate="ASTdead02a"
			id="ASTDEAD02A">
			<Position
				x="1736.8"
				y="3303.84"
				z="0"/>
		</Prop>
		<Prop
			Angle="-0.500658"
			EventList=""
			Faction="player0001/teamplayer0001"
			Health="100"
			Team="player0001"
			ThingTemplate="ASTdead02"
			id="ASTDEAD02">
			<Position
				x="1762.4"
				y="3341.72"
				z="0"/>
		</Prop>
		<Prop
			Angle="0"
			EventList=""
			Faction="player0001/teamplayer0001"
			Health="100"
			Team="player0001"
			ThingTemplate="ASTdead01"
			id="ASTdead01">
			<Position
				x="1790.87"
				y="3342.85"
				z="0"/>
		</Prop>
		<Prop
			Angle="0"
			EventList=""
			Faction="player0001/teamplayer0001"
			Health="100"
			Team="player0001"
			ThingTemplate="ASTshrub01"
			id="ASTshrub01">
			<Position
				x="633.09"
				y="2662.2"
				z="0"/>
		</Prop>
		<Prop
			Angle="2.44454"
			EventList=""
			Faction="player0001/teamplayer0001"
			Health="100"
			Team="player0001"
			ThingTemplate="ASTdead05"
			id="ASTDEAD05">
			<Position
				x="660.556"
				y="2678.8"
				z="0"/>
		</Prop>
		<Prop
			Angle="0"
			EventList=""
			Faction="player0001/teamplayer0001"
			Health="100"
			Team="player0001"
			ThingTemplate="ASTdead05"
			id="ASTDEAD05">
			<Position
				x="613.058"
				y="2620.48"
				z="0"/>
		</Prop>
		<Prop
			Angle="2.95355"
			EventList=""
			Faction="player0001/teamplayer0001"
			Health="100"
			Team="player0001"
			ThingTemplate="ASTdead04"
			id="ASTDEAD04">
			<Position
				x="632.251"
				y="2669.23"
				z="0"/>
		</Prop>
		<Prop
			Angle="0.626159"
			EventList=""
			Faction="player0001/teamplayer0001"
			Health="100"
			Team="player0001"
			ThingTemplate="ASTdead02a"
			id="ASTDEAD02A">
			<Position
				x="595.04"
				y="2611.76"
				z="0"/>
		</Prop>
		<Prop
			Angle="-0.500658"
			EventList=""
			Faction="player0001/teamplayer0001"
			Health="100"
			Team="player0001"
			ThingTemplate="ASTdead02"
			id="ASTDEAD02">
			<Position
				x="620.634"
				y="2649.64"
				z="0"/>
		</Prop>
		<Prop
			Angle="0"
			EventList=""
			Faction="player0001/teamplayer0001"
			Health="100"
			Team="player0001"
			ThingTemplate="ASTdead01"
			id="ASTdead01">
			<Position
				x="649.103"
				y="2650.77"
				z="0"/>
		</Prop>
		<Prop
			Angle="0"
			EventList=""
			Faction="player0001/teamplayer0001"
			Health="100"
			Team="player0001"
			ThingTemplate="ASTshrub01"
			id="ASTshrub01">
			<Position
				x="961.291"
				y="2885.32"
				z="0"/>
		</Prop>
		<Prop
			Angle="2.44454"
			EventList=""
			Faction="player0001/teamplayer0001"
			Health="100"
			Team="player0001"
			ThingTemplate="ASTdead05"
			id="ASTDEAD05">
			<Position
				x="988.757"
				y="2901.92"
				z="0"/>
		</Prop>
		<Prop
			Angle="0"
			EventList=""
			Faction="player0001/teamplayer0001"
			Health="100"
			Team="player0001"
			ThingTemplate="ASTdead05"
			id="ASTDEAD05">
			<Position
				x="941.26"
				y="2843.6"
				z="0"/>
		</Prop>
		<Prop
			Angle="2.95355"
			EventList=""
			Faction="player0001/teamplayer0001"
			Health="100"
			Team="player0001"
			ThingTemplate="ASTdead04"
			id="ASTDEAD04">
			<Position
				x="960.452"
				y="2892.35"
				z="0"/>
		</Prop>
		<Prop
			Angle="0.626159"
			EventList=""
			Faction="player0001/teamplayer0001"
			Health="100"
			Team="player0001"
			ThingTemplate="ASTdead02a"
			id="ASTDEAD02A">
			<Position
				x="923.242"
				y="2834.88"
				z="0"/>
		</Prop>
		<Prop
			Angle="-0.500658"
			EventList=""
			Faction="player0001/teamplayer0001"
			Health="100"
			Team="player0001"
			ThingTemplate="ASTdead02"
			id="ASTDEAD02">
			<Position
				x="948.835"
				y="2872.76"
				z="0"/>
		</Prop>
		<Prop
			Angle="0"
			EventList=""
			Faction="player0001/teamplayer0001"
			Health="100"
			Team="player0001"
			ThingTemplate="ASTdead01"
			id="ASTdead01">
			<Position
				x="977.304"
				y="2873.88"
				z="0"/>
		</Prop>
		<Prop
			Angle="-0.640727"
			EventList=""
			Faction="player0001/teamplayer0001"
			Health="100"
			Team="player0001"
			ThingTemplate="ITRocks02"
			id="ITROCKS02">
			<Position
				x="1013.96"
				y="3658.89"
				z="0"/>
		</Prop>
		<Prop
			Angle="-1.98646"
			EventList=""
			Faction="NOD5/teamNOD5"
			Health="100"
			Team="NOD5"
			ThingTemplate="ITRocks02"
			id="ITROCKS02">
			<Position
				x="847.288"
				y="2964.8"
				z="0"/>
		</Prop>
		<Prop
			Angle="-0.640727"
			EventList=""
			Faction="NOD5/teamNOD5"
			Health="100"
			Team="NOD5"
			ThingTemplate="ITRocks02"
			id="ITROCKS02">
			<Position
				x="853.048"
				y="3024.35"
				z="0"/>
		</Prop>
		<Prop
			Angle="-0.640727"
			EventList=""
			Faction="player0001/teamplayer0001"
			Health="100"
			Team="player0001"
			ThingTemplate="ITRocks02"
			id="ITROCKS02">
			<Position
				x="541.28"
				y="2848.48"
				z="0"/>
		</Prop>
		<Prop
			Angle="-0.640727"
			EventList=""
			Faction="player0001/teamplayer0001"
			Health="100"
			Team="player0001"
			ThingTemplate="ITRocks02"
			id="ITROCKS02">
			<Position
				x="608.802"
				y="2612.48"
				z="0"/>
		</Prop>
		<Prop
			Angle="-0.640727"
			EventList=""
			Faction="player0001/teamplayer0001"
			Health="100"
			Team="player0001"
			ThingTemplate="ITRocks02"
			id="ITROCKS02">
			<Position
				x="937.758"
				y="3179.85"
				z="0"/>
		</Prop>
		<Prop
			Angle="-0.640727"
			EventList=""
			Faction="player0001/teamplayer0001"
			Health="100"
			Team="player0001"
			ThingTemplate="ITRocks02"
			id="ITROCKS02">
			<Position
				x="1126.35"
				y="3094.05"
				z="0"/>
		</Prop>
		<Prop
			Angle="-0.640727"
			EventList=""
			Faction="player0001/teamplayer0001"
			Health="100"
			Team="player0001"
			ThingTemplate="ITRocks02"
			id="ITROCKS02">
			<Position
				x="603.599"
				y="2370.03"
				z="0"/>
		</Prop>
		<Prop
			Angle="-2.054"
			EventList=""
			Faction="player0001/teamplayer0001"
			Health="100"
			Team="player0001"
			ThingTemplate="ITRocks02"
			id="ITROCKS02">
			<Position
				x="332.314"
				y="2716.47"
				z="0"/>
		</Prop>
		<Prop
			Angle="-0.640727"
			EventList=""
			Faction="player0001/teamplayer0001"
			Health="100"
			Team="player0001"
			ThingTemplate="ITRocks02"
			id="ITROCKS02">
			<Position
				x="341.718"
				y="2758.6"
				z="0"/>
		</Prop>
		<Prop
			Angle="-0.640727"
			EventList=""
			Faction="player0001/teamplayer0001"
			Health="100"
			Team="player0001"
			ThingTemplate="ITRocks02"
			id="ITROCKS02">
			<Position
				x="1698.09"
				y="3310.5"
				z="0"/>
		</Prop>
		<Prop
			Angle="-0.640727"
			EventList=""
			Faction="NOD4/teamNOD4"
			Health="100"
			Team="NOD4"
			ThingTemplate="ITRocks02"
			id="ITROCKS02">
			<Position
				x="1415.64"
				y="3151.95"
				z="0"/>
		</Prop>
		<Prop
			Angle="-0.640727"
			EventList=""
			Faction="player0001/teamplayer0001"
			Health="100"
			Team="player0001"
			ThingTemplate="ITRocks02"
			id="ITROCKS02">
			<Position
				x="1039.19"
				y="2958.81"
				z="0"/>
		</Prop>
		<Prop
			Angle="-3.07599"
			EventList=""
			Faction="player0001/teamplayer0001"
			Health="100"
			Team="player0001"
			ThingTemplate="ITRocks02"
			id="ITROCKS02">
			<Position
				x="1607.46"
				y="3002.73"
				z="0"/>
		</Prop>
		<Prop
			Angle="-1.27091"
			EventList=""
			Faction="player0001/teamplayer0001"
			Health="100"
			Team="player0001"
			ThingTemplate="ITRocks02"
			id="ITROCKS02">
			<Position
				x="1926.69"
				y="3009.69"
				z="0"/>
		</Prop>
		<Prop
			Angle="-1.27091"
			EventList=""
			Faction="player0001/teamplayer0001"
			Health="100"
			Team="player0001"
			ThingTemplate="ITRocks02"
			id="ITROCKS02">
			<Position
				x="1755.36"
				y="3080.95"
				z="0"/>
		</Prop>
		<Prop
			Angle="-0.268186"
			EventList=""
			Faction="player0001/teamplayer0001"
			Health="100"
			Team="player0001"
			ThingTemplate="ITRocks02"
			id="ITROCKS02">
			<Position
				x="887.584"
				y="1751.35"
				z="0"/>
		</Prop>
		<Prop
			Angle="-1.27091"
			EventList=""
			Faction="player0001/teamplayer0001"
			Health="100"
			Team="player0001"
			ThingTemplate="ITRocks02"
			id="ITROCKS02">
			<Position
				x="938.294"
				y="1897.52"
				z="0"/>
		</Prop>
		<Prop
			Angle="-1.27091"
			EventList=""
			Faction="player0001/teamplayer0001"
			Health="100"
			Team="player0001"
			ThingTemplate="ITRocks02"
			id="ITROCKS02">
			<Position
				x="211.849"
				y="611.598"
				z="0"/>
		</Prop>
		<Prop
			Angle="-1.27091"
			EventList=""
			Faction="player0001/teamplayer0001"
			Health="100"
			Team="player0001"
			ThingTemplate="ITRocks02"
			id="ITROCKS02">
			<Position
				x="672.337"
				y="1141.7"
				z="0"/>
		</Prop>
		<Prop
			Angle="-1.27091"
			EventList=""
			Faction="player0001/teamplayer0001"
			Health="100"
			Team="player0001"
			ThingTemplate="ITRocks02"
			id="ITROCKS02">
			<Position
				x="773.976"
				y="1413.45"
				z="0"/>
		</Prop>
		<Prop
			Angle="-1.27091"
			EventList=""
			Faction="player0001/teamplayer0001"
			Health="100"
			Team="player0001"
			ThingTemplate="ITRocks02"
			id="ITROCKS02">
			<Position
				x="1024.02"
				y="1413.99"
				z="0"/>
		</Prop>
		<Prop
			Angle="-1.27091"
			EventList=""
			Faction="player0001/teamplayer0001"
			Health="100"
			Team="player0001"
			ThingTemplate="ITRocks02"
			id="ITROCKS02">
			<Position
				x="1421.88"
				y="1196.4"
				z="0"/>
		</Prop>
		<Prop
			Angle="-0.640727"
			EventList=""
			Faction="player0001/teamplayer0001"
			Health="100"
			Team="player0001"
			ThingTemplate="ITRocks02"
			id="ITROCKS02">
			<Position
				x="1702.44"
				y="630.927"
				z="0"/>
		</Prop>
		<Prop
			Angle="-0.640727"
			EventList=""
			Faction="player0001/teamplayer0001"
			Health="100"
			Team="player0001"
			ThingTemplate="ITRocks02"
			id="ITROCKS02">
			<Position
				x="1892.26"
				y="702.459"
				z="0"/>
		</Prop>
		<Prop
			Angle="-0.640727"
			EventList=""
			Faction="player0001/teamplayer0001"
			Health="100"
			Team="player0001"
			ThingTemplate="ITRocks02"
			id="ITROCKS02">
			<Position
				x="950.775"
				y="138.528"
				z="0"/>
		</Prop>
		<Prop
			Angle="-0.640727"
			EventList=""
			Faction="player0001/teamplayer0001"
			Health="100"
			Team="player0001"
			ThingTemplate="ITRocks02"
			id="ITROCKS02">
			<Position
				x="906.508"
				y="2502.66"
				z="0"/>
		</Prop>
		<Prop
			Angle="-0.853622"
			EventList=""
			Faction="player0001/teamplayer0001"
			Health="100"
			Team="player0001"
			ThingTemplate="ITRocks02"
			id="ITROCKS02">
			<Position
				x="1052.75"
				y="2451.55"
				z="0"/>
		</Prop>
		<Prop
			Angle="-0.640727"
			EventList=""
			Faction="player0001/teamplayer0001"
			Health="100"
			Team="player0001"
			ThingTemplate="ITRocks02"
			id="ITROCKS02">
			<Position
				x="1036.44"
				y="2263.03"
				z="0"/>
		</Prop>
		<Prop
			Angle="-0.640727"
			EventList=""
			Faction="player0001/teamplayer0001"
			Health="100"
			Team="player0001"
			ThingTemplate="ITRocks02"
			id="ITROCKS02">
			<Position
				x="1393.95"
				y="1885.07"
				z="0"/>
		</Prop>
		<Prop
			Angle="-1.59338"
			EventList=""
			Faction="player0001/teamplayer0001"
			Health="100"
			Team="player0001"
			ThingTemplate="ITRocks01"
			id="ITRocks01">
			<Position
				x="1346.57"
				y="1872.59"
				z="0"/>
		</Prop>
		<Prop
			Angle="2.82544"
			EventList=""
			Faction="player0001/teamplayer0001"
			Health="100"
			Team="player0001"
			ThingTemplate="ITRocks02"
			id="ITROCKS02">
			<Position
				x="1326.89"
				y="1960.28"
				z="0"/>
		</Prop>
		<Prop
			Angle="1.95952"
			EventList=""
			Faction="player0001/teamplayer0001"
			Health="100"
			Team="player0001"
			ThingTemplate="ITRocks03"
			id="ITROCKS03">
			<Position
				x="1359.19"
				y="1918.83"
				z="0"/>
		</Prop>
		<Prop
			Angle="-1.30256"
			EventList=""
			Faction="player0001/teamplayer0001"
			Health="100"
			Team="player0001"
			ThingTemplate="ASTshrub01"
			id="ASTshrub01">
			<Position
				x="1951.61"
				y="2116.81"
				z="0"/>
		</Prop>
		<Prop
			Angle="1.14198"
			EventList=""
			Faction="player0001/teamplayer0001"
			Health="100"
			Team="player0001"
			ThingTemplate="ASTdead05"
			id="ASTDEAD05">
			<Position
				x="1988.47"
				y="2121.78"
				z="0"/>
		</Prop>
		<Prop
			Angle="-1.30256"
			EventList=""
			Faction="player0001/teamplayer0001"
			Health="100"
			Team="player0001"
			ThingTemplate="ASTdead05"
			id="ASTDEAD05">
			<Position
				x="1932.28"
				y="2127.47"
				z="0"/>
		</Prop>
		<Prop
			Angle="1.65099"
			EventList=""
			Faction="player0001/teamplayer0001"
			Health="100"
			Team="player0001"
			ThingTemplate="ASTdead04"
			id="ASTDEAD04">
			<Position
				x="1971.74"
				y="2146.54"
				z="0"/>
		</Prop>
		<Prop
			Angle="-0.676404"
			EventList=""
			Faction="player0001/teamplayer0001"
			Health="100"
			Team="player0001"
			ThingTemplate="ASTdead02a"
			id="ASTDEAD02A">
			<Position
				x="1942.55"
				y="2119.93"
				z="0"/>
		</Prop>
		<Prop
			Angle="-1.80322"
			EventList=""
			Faction="player0001/teamplayer0001"
			Health="100"
			Team="player0001"
			ThingTemplate="ASTdead02"
			id="ASTDEAD02">
			<Position
				x="1957.25"
				y="2130.64"
				z="0"/>
		</Prop>
		<Prop
			Angle="-1.30256"
			EventList=""
			Faction="player0001/teamplayer0001"
			Health="100"
			Team="player0001"
			ThingTemplate="ASTdead01"
			id="ASTdead01">
			<Position
				x="1958.41"
				y="2125.39"
				z="0"/>
		</Prop>
		<Prop
			Angle="0.0310463"
			EventList=""
			Faction="player0001/teamplayer0001"
			Health="100"
			Team="player0001"
			ThingTemplate="ITPDeadP01"
			id="ITPDEADP01">
			<Position
				x="1843.3"
				y="1641.93"
				z="0"/>
		</Prop>
		<Prop
			Angle="-0.758374"
			EventList=""
			Faction="player0001/teamplayer0001"
			Health="100"
			Team="player0001"
			ThingTemplate="ASTdead02"
			id="ASTDEAD02">
			<Position
				x="506.007"
				y="711.741"
				z="0"/>
		</Prop>
		<Prop
			Angle="0"
			EventList=""
			Faction="player0001/teamplayer0001"
			Health="100"
			Team="player0001"
			ThingTemplate="ASTdead01"
			id="ASTdead01">
			<Position
				x="498.49"
				y="787.846"
				z="0"/>
		</Prop>
		<Prop
			Angle="-0.513119"
			EventList=""
			Faction="player0001/teamplayer0001"
			Health="100"
			Team="player0001"
			ThingTemplate="ASTdead02a"
			id="ASTDEAD02A">
			<Position
				x="460.013"
				y="763.556"
				z="0"/>
		</Prop>
		<Prop
			Angle="0"
			EventList=""
			Faction="player0001/teamplayer0001"
			Health="100"
			Team="player0001"
			ThingTemplate="ASTdead03"
			id="ASTdead03">
			<Position
				x="488.388"
				y="769.118"
				z="0"/>
		</Prop>
		<Prop
			Angle="-0.115005"
			EventList=""
			Faction="player0001/teamplayer0001"
			Health="100"
			Team="player0001"
			ThingTemplate="ASTdead03"
			id="ASTdead03">
			<Position
				x="265.849"
				y="335.806"
				z="0"/>
		</Prop>
		<Prop
			Angle="0"
			EventList=""
			Faction="player0001/teamplayer0001"
			Health="100"
			Team="player0001"
			ThingTemplate="ASTdead05"
			id="ASTDEAD05">
			<Position
				x="232.837"
				y="372.841"
				z="0"/>
		</Prop>
		<Prop
			Angle="0"
			EventList=""
			Faction="player0001/teamplayer0001"
			Health="100"
			Team="player0001"
			ThingTemplate="ASTdead04"
			id="ASTDEAD04">
			<Position
				x="253.541"
				y="359.548"
				z="0"/>
		</Prop>
		<Prop
			Angle="0"
			EventList=""
			Faction="player0001/teamplayer0001"
			Health="100"
			Team="player0001"
			ThingTemplate="ASTdead04"
			id="ASTDEAD04">
			<Position
				x="100.071"
				y="171.588"
				z="0"/>
		</Prop>
		<Prop
			Angle="0"
			EventList=""
			Faction="player0001/teamplayer0001"
			Health="100"
			Team="player0001"
			ThingTemplate="ASTdead02a"
			id="ASTDEAD02A">
			<Position
				x="147.99"
				y="105.836"
				z="0"/>
		</Prop>
		<Prop
			Angle="1.38721"
			EventList=""
			Faction="player0001/teamplayer0001"
			Health="100"
			Team="player0001"
			ThingTemplate="ASTdead04"
			id="ASTDEAD04">
			<Position
				x="151.027"
				y="154.724"
				z="0"/>
		</Prop>
		<Prop
			Angle="0"
			EventList=""
			Faction="player0001/teamplayer0001"
			Health="100"
			Team="player0001"
			ThingTemplate="ASTshrub01"
			id="ASTshrub01">
			<Position
				x="138.472"
				y="128.864"
				z="0"/>
		</Prop>
		<Prop
			Angle="0"
			EventList=""
			Faction="player0001/teamplayer0001"
			Health="100"
			Team="player0001"
			ThingTemplate="ASTdead05"
			id="ASTDEAD05">
			<Position
				x="99.0394"
				y="72.8636"
				z="0"/>
		</Prop>
		<Prop
			Angle="2.95355"
			EventList=""
			Faction="player0001/teamplayer0001"
			Health="100"
			Team="player0001"
			ThingTemplate="ASTdead04"
			id="ASTDEAD04">
			<Position
				x="118.232"
				y="121.612"
				z="0"/>
		</Prop>
		<Prop
			Angle="-0.500658"
			EventList=""
			Faction="player0001/teamplayer0001"
			Health="100"
			Team="player0001"
			ThingTemplate="ASTdead02"
			id="ASTDEAD02">
			<Position
				x="109.886"
				y="94.4537"
				z="0"/>
		</Prop>
		<Prop
			Angle="0"
			EventList=""
			Faction="player0001/teamplayer0001"
			Health="100"
			Team="player0001"
			ThingTemplate="ASTdead01"
			id="ASTdead01">
			<Position
				x="137.583"
				y="99.3902"
				z="0"/>
		</Prop>
		<Prop
			Angle="-2.10654"
			EventList=""
			Faction="player0001/teamplayer0001"
			Health="100"
			Team="player0001"
			ThingTemplate="ITRocks02"
			id="ITROCKS02">
			<Position
				x="194.441"
				y="412.12"
				z="0"/>
		</Prop>
		<Prop
			Angle="-3.0592"
			EventList=""
			Faction="player0001/teamplayer0001"
			Health="100"
			Team="player0001"
			ThingTemplate="ITRocks01"
			id="ITRocks01">
			<Position
				x="172.609"
				y="439.222"
				z="0"/>
		</Prop>
		<Prop
			Angle="0"
			EventList=""
			Faction="PlyrNeutral/teamPlyrNeutral"
			Health="100"
			Team="PlyrNeutral"
			ThingTemplate="HealCrate"
			id="HealCrate">
			<Position
				x="1610.98"
				y="2830.76"
				z="0"/>
		</Prop>
		<Prop
			Angle="0"
			EventList=""
			Faction="PlyrNeutral/teamPlyrNeutral"
			Health="100"
			Team="PlyrNeutral"
			ThingTemplate="TiberiumField"
			id="TiberiumField">
			<Position
				x="1173.94"
				y="861.847"
				z="-40"/>
		</Prop>
		<Prop
			Angle="0"
			EventList=""
			Faction="PlyrNeutral/teamPlyrNeutral"
			Health="100"
			Team="PlyrNeutral"
			ThingTemplate="VeterancyCrate"
			id="VeterancyCrate">
			<Position
				x="1833.41"
				y="2728.99"
				z="0"/>
		</Prop>
		<Prop
			Angle="0"
			EventList=""
			Faction="PlyrNeutral/teamPlyrNeutral"
			Health="100"
			Team="PlyrNeutral"
			ThingTemplate="VeterancyCrate"
			id="VeterancyCrate">
			<Position
				x="1831.98"
				y="931.271"
				z="0"/>
		</Prop>
		<Prop
			Angle="2.28021"
			EventList=""
			Faction="player0001/teamplayer0001"
			Health="100"
			Team="player0001"
			ThingTemplate="ITRocks02"
			id="ITROCKS02">
			<Position
				x="1417.34"
				y="2083.02"
				z="0"/>
		</Prop>
		<Prop
			Angle="-1.2999"
			EventList=""
			Faction="player0001/teamplayer0001"
			Health="100"
			Team="player0001"
			ThingTemplate="ITRocks01"
			id="ITRocks01">
			<Position
				x="1662.98"
				y="1769.61"
				z="0"/>
		</Prop>
		<Prop
			Angle="-2.26895"
			EventList=""
			Faction="player0001/teamplayer0001"
			Health="100"
			Team="player0001"
			ThingTemplate="ITRocks02"
			id="ITROCKS02">
			<Position
				x="1618.68"
				y="1796.99"
				z="0"/>
		</Prop>
		<Prop
			Angle="-3.13487"
			EventList=""
			Faction="player0001/teamplayer0001"
			Health="100"
			Team="player0001"
			ThingTemplate="ITRocks03"
			id="ITROCKS03">
			<Position
				x="1659.84"
				y="1813.44"
				z="0"/>
		</Prop>
		<Prop
			Angle="0"
			EventList=""
			Faction="player0001/teamplayer0001"
			Health="100"
			Team="player0001"
			ThingTemplate="ITPDebris01"
			id="ITPDEBRIS01">
			<Position
				x="1263.82"
				y="1565.55"
				z="0"/>
		</Prop>
		<Prop
			Angle="0"
			EventList=""
			Faction="player0001/teamplayer0001"
			Health="100"
			Team="player0001"
			ThingTemplate="ITPDebris01"
			id="ITPDEBRIS01">
			<Position
				x="1149.65"
				y="1489.18"
				z="0"/>
		</Prop>
		<Prop
			Angle="-0.756925"
			EventList=""
			Faction="player0001/teamplayer0001"
			Health="100"
			Team="player0001"
			ThingTemplate="ITPDebris05"
			id="ITPDEBRIS05">
			<Position
				x="1246.82"
				y="1447.1"
				z="0"/>
		</Prop>
		<Prop
			Angle="0"
			EventList=""
			Faction="player0001/teamplayer0001"
			Health="100"
			Team="player0001"
			ThingTemplate="ITPDebris03"
			id="ITPDEBRIS03">
			<Position
				x="1420.3"
				y="1719.38"
				z="0"/>
		</Prop>
		<Prop
			Angle="0"
			EventList=""
			Faction="player0001/teamplayer0001"
			Health="100"
			Team="player0001"
			ThingTemplate="ITPDebris04"
			id="ITPDEBRIS04">
			<Position
				x="1414.19"
				y="1569.86"
				z="0"/>
		</Prop>
		<Prop
			Angle="-1.7807"
			EventList=""
			Faction="player0001/teamplayer0001"
			Health="100"
			Team="player0001"
			ThingTemplate="ITPDeadP03"
			id="ITPDEADP03">
			<Position
				x="1166.46"
				y="1256.77"
				z="0"/>
		</Prop>
		<Prop
			Angle="-2.12402"
			EventList=""
			Faction="player0001/teamplayer0001"
			Health="100"
			Team="player0001"
			ThingTemplate="ITRocks06"
			id="ITROCKS06">
			<Position
				x="1621.59"
				y="1249.46"
				z="0"/>
		</Prop>
		<Prop
			Angle="-2.65664"
			EventList=""
			Faction="player0001/teamplayer0001"
			Health="100"
			Team="player0001"
			ThingTemplate="ITRocks04"
			id="ITROCKS04">
			<Position
				x="1624.82"
				y="1230.88"
				z="0"/>
		</Prop>
		<Prop
			Angle="-1.50957"
			EventList=""
			Faction="player0001/teamplayer0001"
			Health="100"
			Team="player0001"
			ThingTemplate="ITRocks04"
			id="ITROCKS04">
			<Position
				x="1647.17"
				y="1310.98"
				z="0"/>
		</Prop>
		<Prop
			Angle="-2.61428"
			EventList=""
			Faction="player0001/teamplayer0001"
			Health="100"
			Team="player0001"
			ThingTemplate="ITRocks08"
			id="ITROCKS08">
			<Position
				x="1632.42"
				y="1291.9"
				z="0"/>
		</Prop>
		<Prop
			Angle="0"
			EventList=""
			Faction="player0001/teamplayer0001"
			Health="100"
			Team="player0001"
			ThingTemplate="ASTshrub01"
			id="ASTshrub01">
			<Position
				x="1092.98"
				y="300.249"
				z="0"/>
		</Prop>
		<Prop
			Angle="2.44454"
			EventList=""
			Faction="player0001/teamplayer0001"
			Health="100"
			Team="player0001"
			ThingTemplate="ASTdead05"
			id="ASTDEAD05">
			<Position
				x="1120.44"
				y="316.849"
				z="0"/>
		</Prop>
		<Prop
			Angle="0"
			EventList=""
			Faction="player0001/teamplayer0001"
			Health="100"
			Team="player0001"
			ThingTemplate="ASTdead05"
			id="ASTDEAD05">
			<Position
				x="1072.94"
				y="258.529"
				z="0"/>
		</Prop>
		<Prop
			Angle="2.95355"
			EventList=""
			Faction="player0001/teamplayer0001"
			Health="100"
			Team="player0001"
			ThingTemplate="ASTdead04"
			id="ASTDEAD04">
			<Position
				x="1092.14"
				y="307.277"
				z="0"/>
		</Prop>
		<Prop
			Angle="0.626159"
			EventList=""
			Faction="player0001/teamplayer0001"
			Health="100"
			Team="player0001"
			ThingTemplate="ASTdead02a"
			id="ASTDEAD02A">
			<Position
				x="1054.93"
				y="249.807"
				z="0"/>
		</Prop>
		<Prop
			Angle="-0.500658"
			EventList=""
			Faction="player0001/teamplayer0001"
			Health="100"
			Team="player0001"
			ThingTemplate="ASTdead02"
			id="ASTDEAD02">
			<Position
				x="1080.52"
				y="287.69"
				z="0"/>
		</Prop>
		<Prop
			Angle="0"
			EventList=""
			Faction="player0001/teamplayer0001"
			Health="100"
			Team="player0001"
			ThingTemplate="ASTdead01"
			id="ASTdead01">
			<Position
				x="1108.99"
				y="288.814"
				z="0"/>
		</Prop>
		<Prop
			Angle="0"
			EventList=""
			Faction="player0001/teamplayer0001"
			Health="100"
			Team="player0001"
			ThingTemplate="ITPDeadP03"
			id="ITPDEADP03">
			<Position
				x="817.595"
				y="294.628"
				z="0"/>
		</Prop>
		<Prop
			Angle="-2.06551"
			EventList=""
			Faction="player0001/teamplayer0001"
			Health="100"
			Team="player0001"
			ThingTemplate="ITPDeadP01"
			id="ITPDEADP01">
			<Position
				x="647.26"
				y="220.06"
				z="0"/>
		</Prop>
		<Prop
			Angle="0"
			EventList=""
			Faction="PlyrNeutral/teamPlyrNeutral"
			Health="100"
			Team="PlyrNeutral"
			ThingTemplate="Rubble_Titan02"
			id="Rubble_Titan02">
			<Position
				x="295.82"
				y="560.36"
				z="0"/>
		</Prop>
		<Prop
			Angle="0.952655"
			EventList=""
			Faction="player0001/teamplayer0001"
			Health="100"
			Team="player0001"
			ThingTemplate="ITRocks02"
			id="ITROCKS02">
			<Position
				x="447.242"
				y="552.903"
				z="0"/>
		</Prop>
		<Prop
			Angle="-0.895307"
			EventList=""
			Faction="player0001/teamplayer0001"
			Health="100"
			Team="player0001"
			ThingTemplate="ITRocks01"
			id="ITRocks01">
			<Position
				x="374.713"
				y="567.194"
				z="0"/>
		</Prop>
		<Prop
			Angle="0"
			EventList=""
			Faction="player0001/teamplayer0001"
			Health="100"
			Team="player0001"
			ThingTemplate="ITRocks01"
			id="ITRocks01">
			<Position
				x="460.791"
				y="505.812"
				z="0"/>
		</Prop>
		<Prop
			Angle="-1.86436"
			EventList=""
			Faction="player0001/teamplayer0001"
			Health="100"
			Team="player0001"
			ThingTemplate="ITRocks02"
			id="ITROCKS02">
			<Position
				x="373.566"
				y="484.162"
				z="0"/>
		</Prop>
		<Prop
			Angle="-2.73028"
			EventList=""
			Faction="player0001/teamplayer0001"
			Health="100"
			Team="player0001"
			ThingTemplate="ITRocks03"
			id="ITROCKS03">
			<Position
				x="414.275"
				y="517.385"
				z="0"/>
		</Prop>
		<Prop
			Angle="-1.71914"
			EventList=""
			Faction="PlyrNeutral/teamPlyrNeutral"
			Health="100"
			Team="PlyrNeutral"
			ThingTemplate="TiberiumFieldBlue"
			id="TiberiumFieldBlue">
			<Position
				x="1174.38"
				y="851.646"
				z="0"/>
		</Prop>
		<Road
			id="ItalyDirtRoad01"/>
		<MapMetaData
			BorderSize="15"
			CRC="0"
			Description="Map:Commando_m02/Desc"
			DisplayName="[GDI] Sandstorm"
			FileName="Data"
			Height="430"
			IsMultiplayer="false"
			IsOfficial="false"
			NumPlayers="1"
			Width="230">
			<StartPosition
				Name="InitialCameraPosition">
				<Position
					x="212.845"
					y="336.913"
					z="0"/>
			</StartPosition>
			<StartPosition
				Name="Player_1_Start">
				<Position
					x="0"
					y="0"
					z="0"/>
			</StartPosition>
		</MapMetaData>
		<EnvironmentData
			Cloud="TSCloudMed"
			Environment="EVDefault"
			Macro="TSNoiseUrb"/>
		<WorldDict>
			<RealProperty
				Key="cameraMinHeight"
				Value="170"/>
			<RealProperty
				Key="cameraMaxHeight"
				Value="400"/>
			<BoolProperty
				Key="isLivingWorldScriptHolder"
				Value="false"/>
			<AssetIdProperty
				Key="musicZone"
				Value="MusicPalette_RedZone"/>
			<IntProperty
				Key="weather"
				Value="0"/>
			<StringProperty
				Key="mapName"
				Value="[GDI] Sandstorm"/>
			<StringProperty
				Key="mapDescription"
				Value=""/>
			<IntProperty
				Key="compression"
				Value="1"/>
			<RealProperty
				Key="cameraGroundMinHeight"
				Value="50"/>
			<RealProperty
				Key="cameraGroundMaxHeight"
				Value="2560"/>
			<BoolProperty
				Key="isScenarioMultiplayer"
				Value="false"/>
		</WorldDict>
		<PostEffect
			Effect="BleachByPass_vol"/>
		<PostEffect
			Effect="CM_RedZoneA_LightRays"/>
	</GameMap>
	<TerrainTextureAtlas
		AllowLossyCompression="true"
		AtlasSize="2048"
		id="Commando_m02">
		<Tile
			BaseTexture="ART:Terrain/TDirt_RedZone07.tga"
			NormalTexture="ART:Terrain/TDirt_RedZone07_nrm.tga"
			TextureID="49538242"/>
		<Tile
			BaseTexture="ART:Terrain/TRock_RedZone02.tga"
			NormalTexture="ART:Terrain/TRock_RedZone02_nrm.tga"
			TextureID="262840455"/>
		<Tile
			BaseTexture="ART:Terrain/TRock_RedZone03.tga"
			NormalTexture="ART:Terrain/TRock_RedZone03_nrm.tga"
			TextureID="811033609"/>
		<Tile
			BaseTexture="ART:Terrain/TDirt_RedZone05.tga"
			NormalTexture="ART:Terrain/TDirt_RedZone05_nrm.tga"
			TextureID="847241419"/>
		<Tile
			BaseTexture="ART:Terrain/TRock_RedZone04.tga"
			NormalTexture="ART:Terrain/TRock_RedZone04_nrm.tga"
			TextureID="890421556"/>
		<Tile
			BaseTexture="ART:Terrain/TDirt_RedZone08.tga"
			NormalTexture="ART:Terrain/TDirt_RedZone08_nrm.tga"
			TextureID="897681197"/>
		<Tile
			BaseTexture="ART:Terrain/TDirt_RedZone06.tga"
			NormalTexture="ART:Terrain/TDirt_RedZone06_nrm.tga"
			TextureID="918719450"/>
		<Tile
			BaseTexture="ART:Terrain/TPave_Redzone04.tga"
			NormalTexture="ART:Terrain/TPave_Redzone04_nrm.tga"
			TextureID="1492362055"/>
		<Tile
			BaseTexture="ART:Terrain/TPave_Redzone03.tga"
			NormalTexture="ART:Terrain/TPave_Redzone03_nrm.tga"
			TextureID="1807095070"/>
		<Tile
			BaseTexture="ART:Terrain/TPave_NCarolina03.tga"
			NormalTexture="ART:Terrain/TPave_NCarolina03_nrm.tga"
			TextureID="2331904439"/>
		<Tile
			BaseTexture="ART:Terrain/TDirt_RedZone04.tga"
			NormalTexture="ART:Terrain/TDirt_RedZone04_nrm.tga"
			TextureID="2422374844"/>
		<Tile
			BaseTexture="ART:Terrain/TDirt_RedZone03.tga"
			NormalTexture="ART:Terrain/TDirt_RedZone03_nrm.tga"
			TextureID="2509213345"/>
		<Tile
			BaseTexture="ART:Terrain/TRock_RedZone05.tga"
			NormalTexture="ART:Terrain/TRock_RedZone05_nrm.tga"
			TextureID="2783806449"/>
		<Tile
			BaseTexture="ART:Terrain/CnC3Default.tga"
			NormalTexture="ART:Terrain/CnC3Default_nrm.tga"
			TextureID="2793349879"/>
		<Tile
			BaseTexture="ART:Terrain/TDirt_Aus01b.tga"
			NormalTexture="ART:Terrain/TDirt_Aus01b_nrm.tga"
			TextureID="2821642813"/>
		<Tile
			BaseTexture="ART:Terrain/TDirt_RedZone02.tga"
			NormalTexture="ART:Terrain/TDirt_RedZone02_nrm.tga"
			TextureID="2985835786"/>
		<Tile
			BaseTexture="ART:Terrain/TDirt_RedZone01.tga"
			NormalTexture="ART:Terrain/TDirt_RedZone01_nrm.tga"
			TextureID="3001150286"/>
		<Tile
			BaseTexture="ART:Terrain/TCliff_RedZone01.tga"
			NormalTexture="ART:Terrain/TCliff_RedZone01_nrm.tga"
			TextureID="3141656635"/>
	</TerrainTextureAtlas>
	<GameScriptList
		id="_neutral_">
		<ScriptSet/>
	</GameScriptList>
	<GameScriptList
		id="PLAYER">
		<ScriptSet>
			<Script
				id="AI_Mammoth">
				<Action
					Type="CREATE_NAMED_ON_TEAM_AT_WAYPOINT_WITH_ORIENTATION">
					<ParameterList>
						<ObjectType
							Object="GDIMammoth"/>
					</ParameterList>
				</Action>
				<Action
					Type="SET_MILLISECOND_TIMER">
					<ParameterList/>
				</Action>
				<Action
					Type="ENABLE_SCRIPT">
					<ParameterList/>
				</Action>
			</Script>
			<Script
				id="nod_base3_destroyed 1">
				<Action
					Type="TEAM_SET_SLEEP_STATUS">
					<ParameterList/>
				</Action>
				<Action
					Type="MAP_REVEAL_ALL_PERM">
					<ParameterList/>
				</Action>
				<Action
					Type="TEAM_AI_TRANSFER">
					<ParameterList/>
				</Action>
				<Action
					Type="TEAM_TRANSFER_TO_PLAYER">
					<ParameterList/>
				</Action>
			</Script>
			<Script
				id="gdi_win">
				<Action
					Type="VICTORY">
					<ParameterList/>
				</Action>
			</Script>
			<Script
				id="AI__MAM_02">
				<Action
					Type="CREATE_NAMED_ON_TEAM_AT_WAYPOINT_WITH_ORIENTATION">
					<ParameterList>
						<ObjectType
							Object="GDIMammoth"/>
					</ParameterList>
				</Action>
				<Action
					Type="ENABLE_SCRIPT">
					<ParameterList/>
				</Action>
			</Script>
			<Script
				id="mam_patrol">
				<Action
					Type="MOVE_NAMED_UNIT_TO">
					<ParameterList/>
				</Action>
			</Script>
			<Script
				id="mam__patrol02">
				<Action
					Type="MOVE_NAMED_UNIT_TO">
					<ParameterList/>
				</Action>
			</Script>
			<Script
				id="player_loose">
				<Action
					Type="NO_OP">
					<ParameterList/>
				</Action>
				<Action
					Type="DEFEAT">
					<ParameterList/>
				</Action>
			</Script>
			<Script
				id="nod_base1_destroyed">
				<Action
					Type="MOVE_CAMERA_TO">
					<ParameterList/>
				</Action>
				<Action
					Type="MAP_REVEAL_PERMANENTLY_AT_WAYPOINT">
					<ParameterList/>
				</Action>
				<Action
					Type="SHOW_MILITARY_CAPTION">
					<ParameterList/>
				</Action>
				<Action
					Type="SET_MILLISECOND_TIMER">
					<ParameterList/>
				</Action>
				<Action
					Type="DISABLE_INPUT">
					<ParameterList/>
				</Action>
			</Script>
			<Script
				id="nod_base2_destroyed">
				<Action
					Type="MOVE_CAMERA_TO">
					<ParameterList/>
				</Action>
				<Action
					Type="DISABLE_INPUT">
					<ParameterList/>
				</Action>
				<Action
					Type="MAP_REVEAL_PERMANENTLY_AT_WAYPOINT">
					<ParameterList/>
				</Action>
				<Action
					Type="SHOW_MILITARY_CAPTION">
					<ParameterList/>
				</Action>
				<Action
					Type="SET_MILLISECOND_TIMER">
					<ParameterList/>
				</Action>
			</Script>
			<Script
				id="nod_base3_destroyed">
				<Action
					Type="CREATE_NAMED_ON_TEAM_AT_WAYPOINT">
					<ParameterList>
						<ObjectType
							Object="GDIMCV"/>
					</ParameterList>
				</Action>
				<Action
					Type="EVA_SET_ENABLED_DISABLED">
					<ParameterList/>
				</Action>
				<Action
					Type="MOVE_CAMERA_TO">
					<ParameterList/>
				</Action>
				<Action
					Type="MOVE_NAMED_UNIT_TO">
					<ParameterList/>
				</Action>
				<Action
					Type="PLAYER_GIVE_MONEY">
					<ParameterList/>
				</Action>
				<Action
					Type="TEAM_SET_SLEEP_STATUS">
					<ParameterList/>
				</Action>
				<Action
					Type="PLAYER_GIVE_MONEY">
					<ParameterList/>
				</Action>
				<Action
					Type="SHOW_MILITARY_CAPTION">
					<ParameterList/>
				</Action>
			</Script>
			<Script
				id="IONCANNON_01">
				<Action
					Type="SHOW_MILITARY_CAPTION">
					<ParameterList/>
				</Action>
				<Action
					Type="ENABLE_INPUT">
					<ParameterList/>
				</Action>
				<Action
					Type="SET_MILLISECOND_TIMER">
					<ParameterList/>
				</Action>
			</Script>
			<Script
				id="IONCANNON_FIRED">
				<Action
					Type="SHOW_MILITARY_CAPTION">
					<ParameterList/>
				</Action>
				<Action
					Type="MOVE_CAMERA_TO_NAMED">
					<ParameterList/>
				</Action>
			</Script>
			<Script
				id="nod_base2_shown">
				<Action
					Type="SHOW_MILITARY_CAPTION">
					<ParameterList/>
				</Action>
				<Action
					Type="ENABLE_INPUT">
					<ParameterList/>
				</Action>
				<Action
					Type="MOVE_CAMERA_TO">
					<ParameterList/>
				</Action>
			</Script>
			<Script
				id="Commando_spawn">
				<Action
					Type="MAP_REVEAL_PERMANENTLY_AT_WAYPOINT">
					<ParameterList/>
				</Action>
				<Action
					Type="MAP_REVEAL_ALL">
					<ParameterList/>
				</Action>
				<Action
					Type="EVA_SET_ENABLED_DISABLED">
					<ParameterList/>
				</Action>
				<Action
					Type="ENABLE_SCRIPT">
					<ParameterList/>
				</Action>
				<Action
					Type="CREATE_NAMED_ON_TEAM_AT_WAYPOINT">
					<ParameterList>
						<ObjectType
							Object="GDICommando"/>
					</ParameterList>
				</Action>
				<Action
					Type="CREATE_NAMED_ON_TEAM_AT_WAYPOINT">
					<ParameterList>
						<ObjectType
							Object="GDISniper"/>
					</ParameterList>
				</Action>
				<Action
					Type="CREATE_NAMED_ON_TEAM_AT_WAYPOINT">
					<ParameterList>
						<ObjectType
							Object="GDISniper"/>
					</ParameterList>
				</Action>
			</Script>
			<Script
				id="commando_near_power">
				<Action
					Type="NO_OP">
					<ParameterList/>
				</Action>
				<Action
					Type="NAMED_HUNT">
					<ParameterList/>
				</Action>
			</Script>
			<Script
				id="commando_move">
				<Action
					Type="NO_OP">
					<ParameterList/>
				</Action>
				<Action
					Type="MOVE_NAMED_UNIT_TO">
					<ParameterList/>
				</Action>
				<Action
					Type="MOVE_NAMED_UNIT_TO">
					<ParameterList/>
				</Action>
				<Action
					Type="MOVE_NAMED_UNIT_TO">
					<ParameterList/>
				</Action>
			</Script>
			<ScriptGroup
				id="Intro Script">
				<Script
					id="Intro 01">
					<Action
						Type="SHOW_MILITARY_CAPTION">
						<ParameterList/>
					</Action>
					<Action
						Type="SET_MILLISECOND_TIMER">
						<ParameterList/>
					</Action>
				</Script>
				<Script
					id="Intro 02">
					<Action
						Type="SHOW_MILITARY_CAPTION">
						<ParameterList/>
					</Action>
					<Action
						Type="SET_MILLISECOND_TIMER">
						<ParameterList/>
					</Action>
				</Script>
				<Script
					id="Intro03">
					<Action
						Type="SHOW_MILITARY_CAPTION">
						<ParameterList/>
					</Action>
				</Script>
			</ScriptGroup>
		</ScriptSet>
	</GameScriptList>
	<GameScriptList
		id="NOD">
		<ScriptSet/>
	</GameScriptList>
	<GameScriptList
		id="player0001">
		<ScriptSet/>
	</GameScriptList>
	<GameScriptList
		id="PlyrNeutral">
		<ScriptSet/>
	</GameScriptList>
	<GameScriptList
		id="NOD2">
		<ScriptSet/>
	</GameScriptList>
	<GameScriptList
		id="NODWALL">
		<ScriptSet/>
	</GameScriptList>
	<GameScriptList
		id="NOD3">
		<ScriptSet/>
	</GameScriptList>
	<GameScriptList
		id="NOD4">
		<ScriptSet/>
	</GameScriptList>
	<GameScriptList
		id="GDI">
		<ScriptSet/>
	</GameScriptList>
	<GameScriptList
		id="NOD5">
		<ScriptSet/>
	</GameScriptList>
</AssetDeclaration>